pyepic/__init__.py
pyepic/applications/__init__.py
pyepic/applications/base.py
pyepic/applications/msc_nastran.py
pyepic/applications/openfoam.py
pyepic/applications/zcfd.py
pyepic/applications/zopt.py
pyepic/client/__init__.py
pyepic/client/base.py
pyepic/client/catalog.py
pyepic/client/data.py
pyepic/client/desktop.py
pyepic/client/job.py
pyepic/client/projects.py
pyepic/client/teams.py
pyepic/desktops/__init__.py
pyepic/desktops/desktop.py
pyepic-1.0.24.dist-info/LICENSE
pyepic-1.0.24.dist-info/METADATA
pyepic-1.0.24.dist-info/WHEEL
pyepic-1.0.24.dist-info/top_level.txt
pyepic-1.0.24.dist-info/RECORD
