Metadata-Version: 2.1
Name: pyepic
Version: 1.0.24
Summary: "Python SDK for EPIC"
Home-page: https://github.com/zenotech/pyepic/
Author: "Zenotech"
Author-email: "support@zenotech.com"
License: BSD 3-Clause License
Classifier: License :: OSI Approved :: BSD License
Classifier: Programming Language :: Python :: 3
Classifier: Programming Language :: Python :: 3.5
Classifier: Programming Language :: Python :: 3.6
Classifier: Programming Language :: Python :: 3.7
License-File: LICENSE
Requires-Dist: epiccore >=0.0.28
Requires-Dist: boto3 >=1.16.57
Requires-Dist: urllib3 <1.27,>=1.25.4
